elixir_validations.py
setup.py
sqlalchemy_validations.py
test_elixir.py
test_sqlalchemy.py
sqlalchemy_elixir_validations.egg-info/PKG-INFO
sqlalchemy_elixir_validations.egg-info/SOURCES.txt
sqlalchemy_elixir_validations.egg-info/dependency_links.txt
sqlalchemy_elixir_validations.egg-info/requires.txt
sqlalchemy_elixir_validations.egg-info/top_level.txt