Metadata-Version: 1.0
Name: sqlalchemy-elixir-validations
Version: 0.1.1
Summary: Simple model validations for Elixir and Sqlalchemy
Home-page: http://www.bitbucket.org/radaczynski/sqlalchemy_elixir_validations
Author: Leandro Lameiro & Bartosz Radaczynski
Author-email: lameiro@gmail.com
License: MIT
Keywords: sqlalchemy elixir validations
Platform: UNKNOWN
Classifier: License :: OSI Approved :: MIT License
Classifier: Programming Language :: Python
Classifier: Development Status :: 4 - Beta
Classifier: Intended Audience :: Developers
Classifier: Topic :: Internet
Classifier: Topic :: Software Development :: Libraries :: Python Modules
